LICENCE
README.md
setup.cfg
setup.py
quantificationlib/__init__.py
quantificationlib/bag_generator.py
quantificationlib/base.py
quantificationlib/cvxpy_installed_solvers.py
quantificationlib/data_utils.py
quantificationlib/optimization.py
quantificationlib/search.py
quantificationlib.egg-info/PKG-INFO
quantificationlib.egg-info/SOURCES.txt
quantificationlib.egg-info/dependency_links.txt
quantificationlib.egg-info/requires.txt
quantificationlib.egg-info/top_level.txt
quantificationlib/baselines/__init__.py
quantificationlib/baselines/ac.py
quantificationlib/baselines/cc.py
quantificationlib/binary/__init__.py
quantificationlib/binary/debias.py
quantificationlib/binary/emd.py
quantificationlib/binary/quantiles.py
quantificationlib/decomposition/__init__.py
quantificationlib/decomposition/multiclass.py
quantificationlib/decomposition/ordinal.py
quantificationlib/ensembles/__init__.py
quantificationlib/ensembles/eoq.py
quantificationlib/estimators/__init__.py
quantificationlib/estimators/cross_validation.py
quantificationlib/estimators/ensembles.py
quantificationlib/estimators/frank_and_hall.py
quantificationlib/estimators/ordinal_ddag.py
quantificationlib/estimators/weighted_knn.py
quantificationlib/metrics/__init__.py
quantificationlib/metrics/binary.py
quantificationlib/metrics/multiclass.py
quantificationlib/metrics/ordinal.py
quantificationlib/multiclass/__init__.py
quantificationlib/multiclass/df.py
quantificationlib/multiclass/em.py
quantificationlib/multiclass/energy.py
quantificationlib/multiclass/friedman.py
quantificationlib/multiclass/knn.py
quantificationlib/multiclass/regression.py
quantificationlib/ordinal/__init__.py
quantificationlib/ordinal/ac_ordinal.py
quantificationlib/ordinal/pdf.py
quantificationlib/ordinal/trees.py
quantificationlib/plot/__init__.py
quantificationlib/plot/qlplot.py